mongo_easy/__init__.py
mongo_easy/config.py
mongo_easy/aliasing/__init__.py
mongo_easy/aliasing/alias_generator.py
mongo_easy/aliasing/registry.py
mongo_easy/cli/__init__.py
mongo_easy/cli/main.py
mongo_easy/core/__init__.py
mongo_easy/core/connection.py
mongo_easy/core/crud.py
mongo_easy/core/queries.py
mongo_easy/core/schema.py
mongo_easy/io/__init__.py
mongo_easy/io/backup.py
mongo_easy/io/csv_handler.py
mongo_easy/io/json_handler.py
mongo_easy/utils/__init__.py
mongo_easy/utils/formatter.py
mongo_easy/utils/id_utils.py
mongo_easy/utils/logger.py
mongo_easy-0.1.1.dist-info/licenses/LICENSE
tests/__init__.py
tests/test_aliases.py
tests/test_crud.py
tests/test_io.py
tests/test_queries.py
mongo_easy-0.1.1.dist-info/METADATA
mongo_easy-0.1.1.dist-info/WHEEL
mongo_easy-0.1.1.dist-info/entry_points.txt
mongo_easy-0.1.1.dist-info/top_level.txt
mongo_easy-0.1.1.dist-info/RECORD
