Metadata-Version: 2.4
Name: mongo_easy
Version: 0.1.1
Summary: A simple and intuitive MongoDB helper library for everyone
Home-page: https://github.com/prakhardoneria/mongo_easy
Author: Prakhar Doneria
Author-email: prakhardoneria3@gmail.com
Project-URL: Documentation, https://github.com/prakhardoneria/mongo_easy/docs
Project-URL: Source, https://github.com/prakhardoneria/mongo_easy
Project-URL: Tracker, https://github.com/prakhardoneria/mongo_easy/issues
Classifier: Development Status :: 3 - Alpha
Classifier: Programming Language :: Python :: 3
Classifier: License :: OSI Approved :: MIT License
Classifier: Operating System :: OS Independent
Classifier: Topic :: Database
Requires-Python: >=3.6
License-File: LICENSE
Requires-Dist: pymongo>=3.12.0
Dynamic: author
Dynamic: author-email
Dynamic: classifier
Dynamic: description
Dynamic: description-content-type
Dynamic: home-page
Dynamic: license-file
Dynamic: project-url
Dynamic: requires-dist
Dynamic: requires-python
Dynamic: summary
